s3ranger/__init__.py
s3ranger/config.py
s3ranger/credentials.py
s3ranger/main.py
s3ranger/gateways/s3.py
s3ranger/ui/app.py
s3ranger/ui/app.tcss
s3ranger/ui/constants.py
s3ranger/ui/utils.py
s3ranger/ui/modals/__init__.py
s3ranger/ui/modals/delete_modal.py
s3ranger/ui/modals/download_modal.py
s3ranger/ui/modals/help_modal.py
s3ranger/ui/modals/multi_delete_modal.py
s3ranger/ui/modals/multi_download_modal.py
s3ranger/ui/modals/progress_modal.py
s3ranger/ui/modals/rename_modal.py
s3ranger/ui/modals/upload_modal.py
s3ranger/ui/screens/__init__.py
s3ranger/ui/screens/main_screen.py
s3ranger/ui/screens/move_screen.py
s3ranger/ui/themes/__init__.py
s3ranger/ui/themes/dracula.py
s3ranger/ui/themes/github_dark.py
s3ranger/ui/themes/sepia.py
s3ranger/ui/themes/solarized.py
s3ranger/ui/widgets/__init__.py
s3ranger/ui/widgets/breadcrumb.py
s3ranger/ui/widgets/bucket_list.py
s3ranger/ui/widgets/object_list.py
s3ranger/ui/widgets/progress_widget.py
s3ranger/ui/widgets/sort_overlay.py
s3ranger/ui/widgets/title_bar.py
s3ranger-1.3.0.dist-info/METADATA
s3ranger-1.3.0.dist-info/WHEEL
s3ranger-1.3.0.dist-info/entry_points.txt
s3ranger-1.3.0.dist-info/licenses/LICENSE
s3ranger-1.3.0.dist-info/RECORD
