Metadata-Version: 2.4
Name: s3ranger
Version: 1.3.0
Summary: A terminal-based user interface for browsing and managing AWS S3 buckets and objects
Project-URL: Homepage, https://github.com/Sharashchandra/s3ranger
Project-URL: Repository, https://github.com/Sharashchandra/s3ranger
Project-URL: Issues, https://github.com/Sharashchandra/s3ranger/issues
Author-email: Sharashchandra <sharashchandra1998@gmail.com>
License:                                  Apache License
License-File: LICENSE
Keywords: aws,cloud,s3,storage,terminal,tui
Classifier: Environment :: Console
Classifier: Intended Audience :: Developers
Classifier: Intended Audience :: System Administrators
Classifier: License :: OSI Approved :: Apache Software License
Classifier: Operating System :: OS Independent
Classifier: Programming Language :: Python :: 3
Classifier: Programming Language :: Python :: 3.11
Classifier: Topic :: System :: Systems Administration
Classifier: Topic :: Utilities
Requires-Python: >=3.11
Requires-Dist: awscli>=1.41.9
Requires-Dist: boto3>=1.39.9
Requires-Dist: click>=8.0.0
Requires-Dist: textual-fspicker>=0.4.1
Requires-Dist: textual>=4.0.0
Requires-Dist: toml>=0.10.2
